qporcupine/__init__.py
qporcupine/alt_sentences.py
qporcupine/feedback.py
qporcupine/infinitive_phrase_detect.py
qporcupine/literals.py
qporcupine/preprocess_utils.py
qporcupine/pseudo_verbs.py
qporcupine/reducer_helper.py
qporcupine/subject_verb_extraction.py
qporcupine/subjects_with_verbs_to_reductions.py
qporcupine/sva_classifier.py
qporcupine/top100.py
qporcupine/data/participlevocabindex.csv
qporcupine/data/reduction_counts.csv
qporcupine/models/participle_model.tfl.data-00000-of-00001
qporcupine/models/participle_model.tfl.index
qporcupine/models/participle_model.tfl.meta
qporcupine/models/participle_model2.tfl.data-00000-of-00001
qporcupine/models/participle_model2.tfl.index
qporcupine/models/participle_model2.tfl.meta
qporcupine-0.0.4.dist-info/METADATA
qporcupine-0.0.4.dist-info/RECORD
qporcupine-0.0.4.dist-info/WHEEL
qporcupine-0.0.4.dist-info/top_level.txt
