Metadata-Version: 2.1
Name: qporcupine
Version: 0.0.4
Summary: Grammar error detection and feedback
Home-page: https://github.com/empirical-org/Quill-NLP-Tools-and-Datasets
Author: Quill.org
Author-email: max@quill.org
License: MIT
Platform: UNKNOWN
Requires-Dist: allennlp (==0.5.1)
Requires-Dist: flask (==0.12.2)
Requires-Dist: gunicorn (==19.7.1)
Requires-Dist: nltk (==3.2.5)
Requires-Dist: numpy (==1.14.2)
Requires-Dist: pandas (==0.19.2)
Requires-Dist: pathlib (==1.0.1)
Requires-Dist: requests (==2.18.4)
Requires-Dist: spacy (==2.0.12)
Requires-Dist: sqlalchemy (==1.2.6)
Requires-Dist: tensorflow (==1.5.1)
Requires-Dist: textacy (==0.6.2)
Requires-Dist: tflearn (==0.3.2)
